Workbook

Sheet Sheet1
B3: Student ID | C3: Name | D3: Math | E3: Science | F3: English | G3: Enrollment Date | H3: Total Marks | I3: Total Persentage | J3: Result | K3: grade | L3: Above 80 In maths & science | M3: AVG ABOVE 60 IN(All) | N3: Student Performance | O3: days
B4: 1001 | C4: Prithwi | D4: 61 | E4: 48 | F4: 76 | G4: 43101 | H4: =SUM(D4:F4) -> 185 | I4: =AVERAGE(D4:F4) -> 61.666667 | J4: =IF(H4>=33,"Pass","Fail") -> Pass | K4: =IF(I4>=80,"A", IF(I4>=60,"B", IF(I4>=40,"C","Fail"))) -> B | L4: =IF(OR(D4>90,E4>90),"Eligible","Not Eligible") -> Not Eligible | M4: =AVERAGEIFS(F2:F21, D2:D21, ">60", E2:E21, ">60") -> 71.5 | N4: =IF(I4>=80,"Top Performer", IF(I4>=60,"Good Performer", IF(I4>=40,"Average","Needs Improvement"))) -> Good Performer | O4: =NOW()-G4 -> 2956.2571
B5: 1002 | C5: Roshan | D5: 78 | E5: 76 | F5: 70 | G5: 43281 | H5: =SUM(Sheet1!$D5:$F5) -> 224 | I5: =AVERAGE(D5:F5) -> 74.666667 | J5: =IF(H5>=33,"Pass","Fail") -> Pass | K5: =IF(I5>=80,"A", IF(I5>=60,"B", IF(I5>=40,"C","Fail"))) -> B | L5: =IF(OR(D5>90,E5>90),"Eligible","Not Eligible") -> Not Eligible | M5: =AVERAGEIFS(F3:F22, D3:D22, ">60", E3:E22, ">60") -> 70.222222 | N5: =IF(I5>=80,"Top Performer", IF(I5>=60,"Good Performer", IF(I5>=40,"Average","Needs Improvement"))) -> Good Performer | O5: =NOW()-G5 -> 2776.2571
B6: 1003 | C6: Devil | D6: 97 | E6: 60 | F6: 51 | G6: 43461 | H6: =SUM(Sheet1!$D6:$F6) -> 208 | I6: =AVERAGE(D6:F6) -> 69.333333 | J6: =IF(H6>=33,"Pass","Fail") -> Pass | K6: =IF(I6>=80,"A", IF(I6>=60,"B", IF(I6>=40,"C","Fail"))) -> B | L6: =IF(OR(D6>90,E6>90),"Eligible","Not Eligible") -> Eligible | M6: =AVERAGEIFS(F4:F23, D4:D23, ">60", E4:E23, ">60") -> 68.7 | N6: =IF(I6>=80,"Top Performer", IF(I6>=60,"Good Performer", IF(I6>=40,"Average","Needs Improvement"))) -> Good Performer | O6: =NOW()-G6 -> 2596.2571
B7: 1004 | C7: Shiv | D7: 74 | E7: 55 | F7: 46 | G7: 43641 | H7: =SUM(Sheet1!$D7:$F7) -> 175 | I7: =AVERAGE(D7:F7) -> 58.333333 | J7: =IF(H7>=33,"Pass","Fail") -> Pass | K7: =IF(I7>=80,"A", IF(I7>=60,"B", IF(I7>=40,"C","Fail"))) -> C | L7: =IF(OR(D7>90,E7>90),"Eligible","Not Eligible") -> Not Eligible | M7: =AVERAGEIFS(F5:F24, D5:D24, ">60", E5:E24, ">60") -> 68.7 | N7: =IF(I7>=80,"Top Performer", IF(I7>=60,"Good Performer", IF(I7>=40,"Average","Needs Improvement"))) -> Average | O7: =NOW()-G7 -> 2416.2571
B8: 1005 | C8: Krishna | D8: 68 | E8: 74 | F8: 84 | G8: 43821 | H8: =SUM(Sheet1!$D8:$F8) -> 226 | I8: =AVERAGE(D8:F8) -> 75.333333 | J8: =IF(H8>=33,"Pass","Fail") -> Pass | K8: =IF(I8>=80,"A", IF(I8>=60,"B", IF(I8>=40,"C","Fail"))) -> B | L8: =IF(OR(D8>90,E8>90),"Eligible","Not Eligible") -> Not Eligible | M8: =AVERAGEIFS(F6:F25, D6:D25, ">60", E6:E25, ">60") -> 68.555556 | N8: =IF(I8>=80,"Top Performer", IF(I8>=60,"Good Performer", IF(I8>=40,"Average","Needs Improvement"))) -> Good Performer | O8: =NOW()-G8 -> 2236.2571
B9: 1006 | C9: Ram | D9: 80 | E9: 70 | F9: 65 | G9: 44001 | H9: =SUM(Sheet1!$D9:$F9) -> 215 | I9: =AVERAGE(D9:F9) -> 71.666667 | J9: =IF(H9>=33,"Pass","Fail") -> Pass | K9: =IF(I9>=80,"A", IF(I9>=60,"B", IF(I9>=40,"C","Fail"))) -> B | L9: =IF(OR(D9>90,E9>90),"Eligible","Not Eligible") -> Not Eligible | M9: =AVERAGEIFS(F7:F26, D7:D25, ">60", E7:E26, ">60") -> #VALUE! | N9: =IF(I9>=80,"Top Performer", IF(I9>=60,"Good Performer", IF(I9>=40,"Average","Needs Improvement"))) -> Good Performer | O9: =NOW()-G9 -> 2056.2571
B10: 1007 | C10: Rahul | D10: 75 | E10: 47 | F10: 78 | G10: 44181 | H10: =SUM(Sheet1!$D10:$F10) -> 200 | I10: =AVERAGE(D10:F10) -> 66.666667 | J10: =IF(H10>=33,"Pass","Fail") -> Pass | K10: =IF(I10>=80,"A", IF(I10>=60,"B", IF(I10>=40,"C","Fail"))) -> B | L10: =IF(OR(D10>90,E10>90),"Eligible","Not Eligible") -> Not Eligible | M10: =AVERAGEIFS(F8:F29, D8:D31, ">60", E8:E27, ">60") -> #VALUE! | N10: =IF(I10>=80,"Top Performer", IF(I10>=60,"Good Performer", IF(I10>=40,"Average","Needs Improvement"))) -> Good Performer | O10: =NOW()-G10 -> 1876.2571
B11: 1008 | C11: Anand | D11: 94 | E11: 67 | F11: 64 | G11: 44361 | H11: =SUM(Sheet1!$D11:$F11) -> 225 | I11: =AVERAGE(D11:F11) -> 75 | J11: =IF(H11>=33,"Pass","Fail") -> Pass | K11: =IF(I11>=80,"A", IF(I11>=60,"B", IF(I11>=40,"C","Fail"))) -> B | L11: =IF(OR(D11>90,E11>90),"Eligible","Not Eligible") -> Eligible | M11: =AVERAGEIFS(F9:F29, D9:D28, ">60", E9:E28, ">60") -> #VALUE! | N11: =IF(I11>=80,"Top Performer", IF(I11>=60,"Good Performer", IF(I11>=40,"Average","Needs Improvement"))) -> Good Performer | O11: =NOW()-G11 -> 1696.2571
B12: 1009 | C12: Sam | D12: 41 | E12: 75 | F12: 56 | G12: 44541 | H12: =SUM(Sheet1!$D12:$F12) -> 172 | I12: =AVERAGE(D12:F12) -> 57.333333 | J12: =IF(H12>=33,"Pass","Fail") -> Pass | K12: =IF(I12>=80,"A", IF(I12>=60,"B", IF(I12>=40,"C","Fail"))) -> C | L12: =IF(OR(D12>90,E12>90),"Eligible","Not Eligible") -> Not Eligible | M12: =AVERAGEIFS(F10:F29, D10:D29, ">60", E10:E29, ">60") -> 66.857143 | N12: =IF(I12>=80,"Top Performer", IF(I12>=60,"Good Performer", IF(I12>=40,"Average","Needs Improvement"))) -> Average | O12: =NOW()-G12 -> 1516.2571
B13: 1010 | C13: Arav | D13: 98 | E13: 54 | F13: 58 | G13: 44721 | H13: =SUM(Sheet1!$D13:$F13) -> 210 | I13: =AVERAGE(D13:F13) -> 70 | J13: =IF(H13>=33,"Pass","Fail") -> Pass | K13: =IF(I13>=80,"A", IF(I13>=60,"B", IF(I13>=40,"C","Fail"))) -> B | L13: =IF(OR(D13>90,E13>90),"Eligible","Not Eligible") -> Eligible | M13: =AVERAGEIFS(F11:F28, D11:D29, ">60", E11:E30, ">60") -> #VALUE! | N13: =IF(I13>=80,"Top Performer", IF(I13>=60,"Good Performer", IF(I13>=40,"Average","Needs Improvement"))) -> Good Performer | O13: =NOW()-G13 -> 1336.2571
B14: 1011 | C14: Madhu | D14: 73 | E14: 79 | F14: 53 | G14: 44901 | H14: =SUM(Sheet1!$D14:$F14) -> 205 | I14: =AVERAGE(D14:F14) -> 68.333333 | J14: =IF(H14>=33,"Pass","Fail") -> Pass | K14: =IF(I14>=80,"A", IF(I14>=60,"B", IF(I14>=40,"C","Fail"))) -> B | L14: =IF(OR(D14>90,E14>90),"Eligible","Not Eligible") -> Not Eligible | M14: =AVERAGEIFS(F12:F29, D12:D29, ">60", E12:E31, ">60") -> #VALUE! | N14: =IF(I14>=80,"Top Performer", IF(I14>=60,"Good Performer", IF(I14>=40,"Average","Needs Improvement"))) -> Good Performer | O14: =NOW()-G14 -> 1156.2571
B15: 1012 | C15: Dany | D15: 85 | E15: 89 | F15: 79 | G15: 45081 | H15: =SUM(Sheet1!$D15:$F15) -> 253 | I15: =AVERAGE(D15:F15) -> 84.333333 | J15: =IF(H15>=33,"Pass","Fail") -> Pass | K15: =IF(I15>=80,"A", IF(I15>=60,"B", IF(I15>=40,"C","Fail"))) -> A | L15: =IF(OR(D15>90,E15>90),"Eligible","Not Eligible") -> Not Eligible | M15: =AVERAGEIFS(F13:F29, D13:D29, ">60", E13:E32, ">60") -> #VALUE! | N15: =IF(I15>=80,"Top Performer", IF(I15>=60,"Good Performer", IF(I15>=40,"Average","Needs Improvement"))) -> Top Performer | O15: =NOW()-G15 -> 976.25707
B16: 1013 | C16: Dragon | D16: 98 | E16: 90 | F16: 97 | G16: 45261 | H16: =SUM(Sheet1!$D16:$F16) -> 285 | I16: =AVERAGE(D16:F16) -> 95 | J16: =IF(H16>=33,"Pass","Fail") -> Pass | K16: =IF(I16>=80,"A", IF(I16>=60,"B", IF(I16>=40,"C","Fail"))) -> A | L16: =IF(OR(D16>90,E16>90),"Eligible","Not Eligible") -> Eligible | M16: =AVERAGEIFS(F14:F29, D14:D29, ">60", E14:E33, ">60") -> #VALUE! | N16: =IF(I16>=80,"Top Performer", IF(I16>=60,"Good Performer", IF(I16>=40,"Average","Needs Improvement"))) -> Top Performer | O16: =NOW()-G16 -> 796.25707
B17: 1014 | C17: Darshan | D17: 93 | E17: 40 | F17: 44 | G17: 45441 | H17: =SUM(Sheet1!$D17:$F17) -> 177 | I17: =AVERAGE(D17:F17) -> 59 | J17: =IF(H17>=33,"Pass","Fail") -> Pass | K17: =IF(I17>=80,"A", IF(I17>=60,"B", IF(I17>=40,"C","Fail"))) -> C | L17: =IF(OR(D17>90,E17>90),"Eligible","Not Eligible") -> Eligible | M17: =AVERAGEIFS(F15:F34, D15:D29, ">60", E15:E34, ">60") -> #VALUE! | N17: =IF(I17>=80,"Top Performer", IF(I17>=60,"Good Performer", IF(I17>=40,"Average","Needs Improvement"))) -> Average | O17: =NOW()-G17 -> 616.25707
B18: 1015 | C18: Raj | D18: 70 | E18: 51 | F18: 75 | G18: 45621 | H18: =SUM(Sheet1!$D18:$F18) -> 196 | I18: =AVERAGE(D18:F18) -> 65.333333 | J18: =IF(H18>=33,"Pass","Fail") -> Pass | K18: =IF(I18>=80,"A", IF(I18>=60,"B", IF(I18>=40,"C","Fail"))) -> B | L18: =IF(OR(D18>90,E18>90),"Eligible","Not Eligible") -> Not Eligible | M18: =AVERAGEIFS(F16:F35, D16:D35, ">60", E16:E35, ">60") -> 68 | N18: =IF(I18>=80,"Top Performer", IF(I18>=60,"Good Performer", IF(I18>=40,"Average","Needs Improvement"))) -> Good Performer | O18: =NOW()-G18 -> 436.25707
B19: 1016 | C19: Radha | D19: 98 | E19: 77 | F19: 60 | G19: 45801 | H19: =SUM(Sheet1!$D19:$F19) -> 235 | I19: =AVERAGE(D19:F19) -> 78.333333 | J19: =IF(H19>=33,"Pass","Fail") -> Pass | K19: =IF(I19>=80,"A", IF(I19>=60,"B", IF(I19>=40,"C","Fail"))) -> B | L19: =IF(OR(D19>90,E19>90),"Eligible","Not Eligible") -> Eligible | M19: =AVERAGEIFS(F17:F36, D17:D36, ">60", E17:E36, ">60") -> 58.333333 | N19: =IF(I19>=80,"Top Performer", IF(I19>=60,"Good Performer", IF(I19>=40,"Average","Needs Improvement"))) -> Good Performer | O19: =NOW()-G19 -> 256.25707
B20: 1017 | C20: Som | D20: 66 | E20: 59 | F20: 40 | G20: 45981 | H20: =SUM(Sheet1!$D20:$F20) -> 165 | I20: =AVERAGE(D20:F20) -> 55 | J20: =IF(H20>=33,"Pass","Fail") -> Pass | K20: =IF(I20>=80,"A", IF(I20>=60,"B", IF(I20>=40,"C","Fail"))) -> C | L20: =IF(OR(D20>90,E20>90),"Eligible","Not Eligible") -> Not Eligible | M20: =AVERAGEIFS(F18:F37, D18:D37, ">60", E18:E37, ">60") -> 58.333333 | N20: =IF(I20>=80,"Top Performer", IF(I20>=60,"Good Performer", IF(I20>=40,"Average","Needs Improvement"))) -> Average | O20: =NOW()-G20 -> 76.257065
B21: 1018 | C21: Asmita | D21: 82 | E21: 48 | F21: 79 | G21: 46161 | H21: =SUM(Sheet1!$D21:$F21) -> 209 | I21: =AVERAGE(D21:F21) -> 69.666667 | J21: =IF(H21>=33,"Pass","Fail") -> Pass | K21: =IF(I21>=80,"A", IF(I21>=60,"B", IF(I21>=40,"C","Fail"))) -> B | L21: =IF(OR(D21>90,E21>90),"Eligible","Not Eligible") -> Not Eligible | M21: =AVERAGEIFS(F19:F38, D19:D38, ">60", E19:E38, ">60") -> 58.333333 | N21: =IF(I21>=80,"Top Performer", IF(I21>=60,"Good Performer", IF(I21>=40,"Average","Needs Improvement"))) -> Good Performer | O21: =NOW()-G21 -> -103.74293
B22: 1019 | C22: Nitesh | D22: 90 | E22: 78 | F22: 60 | G22: 46341 | H22: =SUM(Sheet1!$D22:$F22) -> 228 | I22: =AVERAGE(D22:F22) -> 76 | J22: =IF(H22>=33,"Pass","Fail") -> Pass | K22: =IF(I22>=80,"A", IF(I22>=60,"B", IF(I22>=40,"C","Fail"))) -> B | L22: =IF(OR(D22>90,E22>90),"Eligible","Not Eligible") -> Not Eligible | M22: =AVERAGEIFS(F20:F39, D20:D39, ">60", E20:E39, ">60") -> 57.5 | N22: =IF(I22>=80,"Top Performer", IF(I22>=60,"Good Performer", IF(I22>=40,"Average","Needs Improvement"))) -> Good Performer | O22: =NOW()-G22 -> -283.74293
B23: 1020 | C23: Rohit | D23: 83 | E23: 92 | F23: 55 | G23: 46521 | H23: =SUM(Sheet1!$D23:$F23) -> 230 | I23: =AVERAGE(D23:F23) -> 76.666667 | J23: =IF(H23>=33,"Pass","Fail") -> Pass | K23: =IF(I23>=80,"A", IF(I23>=60,"B", IF(I23>=40,"C","Fail"))) -> B | L23: =IF(OR(D23>90,E23>90),"Eligible","Not Eligible") -> Eligible | M23: =AVERAGEIFS(F21:F40, D21:D40, ">60", E21:E40, ">60") -> 57.5 | N23: =IF(I23>=80,"Top Performer", IF(I23>=60,"Good Performer", IF(I23>=40,"Average","Needs Improvement"))) -> Good Performer | O23: =NOW()-G23 -> -463.74293
I26: Above >50 in maths
I27: Students | J27: =COUNTIF(D4:D23,">50") -> 19
F30: X Look UP Show All Subjects Marks | L30: V Look Up Cell
F31: Student ID | H31: 1007 | L31: Student Id | M31: 1004
F32: Math | H32: {=XLOOKUP(H31,B4:B23, D4:D23)} -> 75 | L32: Student Name | M32: =VLOOKUP(M31,B3:C23,2,) -> Shiv
F33: English | H33: {=XLOOKUP(H31,B5:B24, F5:F24)} -> 78
F34: Science | H34: {=XLOOKUP(H31,B5:B24, E5:E24)} -> 47
I38: Max Marks In Subjects (Indirect)
I39: Maths | K39: {=MAX(INDIRECT("D4:D23"))} -> 98
I40: Science | K40: {=MAX(INDIRECT("E4:E23"))} -> 92
I41: English | K41: {=MAX(INDIRECT("F4:F23"))} -> 97

Sheet Sheet2
B3: Sales ID | C3: Product | D3: Region | E3: Salesperson | F3: Amount | G3: Date | H3: Months | I3: Clasify Discount | J3: Discount Eligibility
B4: 2001 | C4: Keyboard | D4: South | E4: Prithwi | F4: 7048 | G4: 44927 | H4: =TEXT(G4,"MMMM") -> January | I4: =IF(F4<10000,"No Discount", IF(F4<=20000,"5% Discount", IF(F4<=30000,"10% Discount", "15% Discount"))) -> No Discount | J4: =IF(F4>=10000,"Eligible for Discount","No Discount") -> No Discount
B5: 2002 | C5: Printer | D5: West | E5: Roshan | F5: 17428 | G5: 44942 | H5: =TEXT(G5,"MMMM") -> January | I5: =IF(F5<10000,"No Discount", IF(F5<=20000,"5% Discount", IF(F5<=30000,"10% Discount", "15% Discount"))) -> 5% Discount | J5: =IF(F5>=10000,"Eligible for Discount","No Discount") -> Eligible for Discount
B6: 2003 | C6: Mouse | D6: South | E6: Devil | F6: 23672 | G6: 44957 | H6: =TEXT(G6,"MMMM") -> January | I6: =IF(F6<10000,"No Discount", IF(F6<=20000,"5% Discount", IF(F6<=30000,"10% Discount", "15% Discount"))) -> 10% Discount | J6: =IF(F6>=10000,"Eligible for Discount","No Discount") -> Eligible for Discount
B7: 2004 | C7: Printer | D7: East | E7: Shiv | F7: 5264 | G7: 44972 | H7: =TEXT(G7,"MMMM") -> February | I7: =IF(F7<10000,"No Discount", IF(F7<=20000,"5% Discount", IF(F7<=30000,"10% Discount", "15% Discount"))) -> No Discount | J7: =IF(F7>=10000,"Eligible for Discount","No Discount") -> No Discount
B8: 2005 | C8: Keyboard | D8: North | E8: Krishna | F8: 43388 | G8: 44987 | H8: =TEXT(G8,"MMMM") -> March | I8: =IF(F8<10000,"No Discount", IF(F8<=20000,"5% Discount", IF(F8<=30000,"10% Discount", "15% Discount"))) -> 15% Discount | J8: =IF(F8>=10000,"Eligible for Discount","No Discount") -> Eligible for Discount
B9: 2006 | C9: Mouse | D9: North | E9: Ram | F9: 19757 | G9: 45002 | H9: =TEXT(G9,"MMMM") -> March | I9: =IF(F9<10000,"No Discount", IF(F9<=20000,"5% Discount", IF(F9<=30000,"10% Discount", "15% Discount"))) -> 5% Discount | J9: =IF(F9>=10000,"Eligible for Discount","No Discount") -> Eligible for Discount
B10: 2007 | C10: Mouse | D10: East | E10: Rahul | F10: 32058 | G10: 45017 | H10: =TEXT(G10,"MMMM") -> April | I10: =IF(F10<10000,"No Discount", IF(F10<=20000,"5% Discount", IF(F10<=30000,"10% Discount", "15% Discount"))) -> 15% Discount | J10: =IF(F10>=10000,"Eligible for Discount","No Discount") -> Eligible for Discount
B11: 2008 | C11: Keyboard | D11: East | E11: Anand | F11: 46429 | G11: 45032 | H11: =TEXT(G11,"MMMM") -> April | I11: =IF(F11<10000,"No Discount", IF(F11<=20000,"5% Discount", IF(F11<=30000,"10% Discount", "15% Discount"))) -> 15% Discount | J11: =IF(F11>=10000,"Eligible for Discount","No Discount") -> Eligible for Discount
B12: 2009 | C12: Printer | D12: East | E12: Sam | F12: 19746 | G12: 45047 | H12: =TEXT(G12,"MMMM") -> May | I12: =IF(F12<10000,"No Discount", IF(F12<=20000,"5% Discount", IF(F12<=30000,"10% Discount", "15% Discount"))) -> 5% Discount | J12: =IF(F12>=10000,"Eligible for Discount","No Discount") -> Eligible for Discount
B13: 2010 | C13: Keyboard | D13: South | E13: Arav | F13: 35185 | G13: 45062 | H13: =TEXT(G13,"MMMM") -> May | I13: =IF(F13<10000,"No Discount", IF(F13<=20000,"5% Discount", IF(F13<=30000,"10% Discount", "15% Discount"))) -> 15% Discount | J13: =IF(F13>=10000,"Eligible for Discount","No Discount") -> Eligible for Discount
B14: 2011 | C14: Keyboard | D14: East | E14: Madhu | F14: 33920 | G14: 45077 | H14: =TEXT(G14,"MMMM") -> May | I14: =IF(F14<10000,"No Discount", IF(F14<=20000,"5% Discount", IF(F14<=30000,"10% Discount", "15% Discount"))) -> 15% Discount | J14: =IF(F14>=10000,"Eligible for Discount","No Discount") -> Eligible for Discount
B15: 2012 | C15: Monitor | D15: North | E15: Dany | F15: 35611 | G15: 45092 | H15: =TEXT(G15,"MMMM") -> June | I15: =IF(F15<10000,"No Discount", IF(F15<=20000,"5% Discount", IF(F15<=30000,"10% Discount", "15% Discount"))) -> 15% Discount | J15: =IF(F15>=10000,"Eligible for Discount","No Discount") -> Eligible for Discount
... B23: 2020 | C23: Printer | D23: West | E23: Rohit | F23: 33953 | G23: 45212 | H23: =TEXT(G23,"MMMM") -> October | I23: =IF(F23<10000,"No Discount", IF(F23<=20000,"5% Discount", IF(F23<=30000,"10% Discount", "15% Discount"))) -> 15% Discount | J23: =IF(F23>=10000,"Eligible for Discount","No Discount") -> Eligible for Discount
B26: VLOOK UP (Price) | F26: Total Sales all region (Keybord) | I26: Sum If Of (Printer And Mouse)
B27: Sales ID | D27: 2005 | F27: North | G27: =SUMIFS(F:F, D:D, "North", C:C, "Keyboard") -> 43388 | I27: Printer | K27: =SUMIF(C2:C21,"Printer",F2:F21) -> 42438
B28: Product price | D28: =VLOOKUP(D27,$B$4:$F$23,5,FALSE) -> 43388 | F28: South | G28: =SUMIFS(F:F, D:D, "South", C:C, "Keyboard") -> 42233 | I28: Mouse | K28: =SUMIF(C2:C21,"Mouse",F2:F21) -> 80764
F29: East | G29: =SUMIFS(F:F, D:D, "East", C:C, "Keyboard") -> 80349
F30: West | G30: =SUMIFS(F:F, D:D, "West", C:C, "Keybord") -> 0
B31: Index and match salesperson
B32: Sales ID | C32: 2005 | I32: Salesperson performance(Devil)
B33: Sales Person | C33: {=INDEX(E2:E21, MATCH(C32, B2:B21, 5))} -> Krishna | E33: X look up priduct name(by id) | I33: Devil perform | J33: {=XLOOKUP(E6, E2:E21, F2:F21, "No Data")} -> 23672
E34: Sales ID | F34: 2005
E35: Product name | F35: {=XLOOKUP(F34,Sheet2!$B$4:$B$23,Sheet2!$C$4:$C$23,"no Data",0)} -> Keyboard
A38: s | B38: Position Of Product By X match | E38: Dynamic Offset(Avg Of 1st 5 Data)
B39: Keyboard | C39: =XMATCH("Keyboard", C2:C21) -> 3 | E39: =AVERAGE(OFFSET(F2,0,0,5)) -> 16049.333
B40: Mouse | C40: =XMATCH("Mouse", C2:C21) -> 5
B41: Printer | C41: =XMATCH("Printer", C2:C21) -> 4
B42: Monitor | C42: =XMATCH("Monitor", C2:C21) -> 14

Sheet Sheet3
A1: Employee ID | B1: Name | C1: Department | D1: Salary | E1: Joining Date | F1: upper name | G1: Since Joining (days) | H1: Bonus | I1: Bonus %
A2: 3001 | B2: Prithwi | C2: Finance | D2: 86766 | E2: 42005 | F2: =UPPER(B2) -> PRITHWI | G2: =NOW()-E2 -> 4052.2571 | H2: =IF(D2>=50000,D2*10%, IF(D2>=40000,D2*5%, 0)) -> 8676.6 | I2: =IF(D2>=50000,"10% Bonus", IF(D2>=40000,"5% Bonus", "No Bonus")) -> 10% Bonus
A3: 3002 | B3: Roshan | C3: Finance | D3: 31943 | E3: 42255 | F3: =UPPER(B3) -> ROSHAN | G3: =NOW()-E3 -> 3802.2571 | H3: =IF(D3>=50000,D3*10%, IF(D3>=40000,D3*5%, 0)) -> 0 | I3: =IF(D3>=50000,"10% Bonus", IF(D3>=40000,"5% Bonus", "No Bonus")) -> No Bonus
A4: 3003 | B4: Devil | C4: HR | D4: 63374 | E4: 42505 | F4: =UPPER(B4) -> DEVIL | G4: =NOW()-E4 -> 3552.2571 | H4: =IF(D4>=50000,D4*10%, IF(D4>=40000,D4*5%, 0)) -> 6337.4 | I4: =IF(D4>=50000,"10% Bonus", IF(D4>=40000,"5% Bonus", "No Bonus")) -> 10% Bonus
A5: 3004 | B5: Shiv | C5: Finance | D5: 109972 | E5: 42755 | F5: =UPPER(B5) -> SHIV | G5: =NOW()-E5 -> 3302.2571 | H5: =IF(D5>=50000,D5*10%, IF(D5>=40000,D5*5%, 0)) -> 10997.2 | I5: =IF(D5>=50000,"10% Bonus", IF(D5>=40000,"5% Bonus", "No Bonus")) -> 10% Bonus
A6: 3005 | B6: Krishna | C6: IT | D6: 54149 | E6: 43005 | F6: =UPPER(B6) -> KRISHNA | G6: =NOW()-E6 -> 3052.2571 | H6: =IF(D6>=50000,D6*10%, IF(D6>=40000,D6*5%, 0)) -> 5414.9 | I6: =IF(D6>=50000,"10% Bonus", IF(D6>=40000,"5% Bonus", "No Bonus")) -> 10% Bonus
A7: 3006 | B7: Ram | C7: IT | D7: 78689 | E7: 43255 | F7: =UPPER(B7) -> RAM | G7: =NOW()-E7 -> 2802.2571 | H7: =IF(D7>=50000,D7*10%, IF(D7>=40000,D7*5%, 0)) -> 7868.9 | I7: =IF(D7>=50000,"10% Bonus", IF(D7>=40000,"5% Bonus", "No Bonus")) -> 10% Bonus
A8: 3007 | B8: Rahul | C8: Marketing | D8: 35960 | E8: 43505 | F8: =UPPER(B8) -> RAHUL | G8: =NOW()-E8 -> 2552.2571 | H8: =IF(D8>=50000,D8*10%, IF(D8>=40000,D8*5%, 0)) -> 0 | I8: =IF(D8>=50000,"10% Bonus", IF(D8>=40000,"5% Bonus", "No Bonus")) -> No Bonus
A9: 3008 | B9: Anand | C9: IT | D9: 91659 | E9: 43755 | F9: =UPPER(B9) -> ANAND | G9: =NOW()-E9 -> 2302.2571 | H9: =IF(D9>=50000,D9*10%, IF(D9>=40000,D9*5%, 0)) -> 9165.9 | I9: =IF(D9>=50000,"10% Bonus", IF(D9>=40000,"5% Bonus", "No Bonus")) -> 10% Bonus
A10: 3009 | B10: Sam | C10: IT | D10: 90423 | E10: 44005 | F10: =UPPER(B10) -> SAM | G10: =NOW()-E10 -> 2052.2571 | H10: =IF(D10>=50000,D10*10%, IF(D10>=40000,D10*5%, 0)) -> 9042.3 | I10: =IF(D10>=50000,"10% Bonus", IF(D10>=40000,"5% Bonus", "No Bonus")) -> 10% Bonus
A11: 3010 | B11: Arav | C11: HR | D11: 107877 | E11: 44255 | F11: =UPPER(B11) -> ARAV | G11: =NOW()-E11 -> 1802.2571 | H11: =IF(D11>=50000,D11*10%, IF(D11>=40000,D11*5%, 0)) -> 10787.7 | I11: =IF(D11>=50000,"10% Bonus", IF(D11>=40000,"5% Bonus", "No Bonus")) -> 10% Bonus
A12: 3011 | B12: Madhu | C12: Finance | D12: 107634 | E12: 44505 | F12: =UPPER(B12) -> MADHU | G12: =NOW()-E12 -> 1552.2571 | H12: =IF(D12>=50000,D12*10%, IF(D12>=40000,D12*5%, 0)) -> 10763.4 | I12: =IF(D12>=50000,"10% Bonus", IF(D12>=40000,"5% Bonus", "No Bonus")) -> 10% Bonus
A13: 3012 | B13: Dany | C13: Finance | D13: 35226 | E13: 44755 | F13: =UPPER(B13) -> DANY | G13: =NOW()-E13 -> 1302.2571 | H13: =IF(D13>=50000,D13*10%, IF(D13>=40000,D13*5%, 0)) -> 0 | I13: =IF(D13>=50000,"10% Bonus", IF(D13>=40000,"5% Bonus", "No Bonus")) -> No Bonus
... A21: 3020 | B21: Rohit | C21: Marketing | D21: 99924 | E21: 46755 | F21: =UPPER(B21) -> ROHIT | G21: =NOW()-E21 -> -697.74293 | H21: =IF(D21>=50000,D21*10%, IF(D21>=40000,D21*5%, 0)) -> 9992.4 | I21: =IF(D21>=50000,"10% Bonus", IF(D21>=40000,"5% Bonus", "No Bonus")) -> 10% Bonus
A24: Count If Num of salary >80000
A25: Dept Name | B25: >80000 count | G25: Emp salary > 100000 rs
A26: IT | B26: =COUNTIFS(C2:C21,"It",D2:D21,">80000") -> 3 | G26: Emp ID | H26: Emp Name | J26: Vlookup salary by emp id
A27: HR | B27: =COUNTIFS(C2:C21,"hr",D2:D21,">80000") -> 2 | D27: Indirect Dept Selection (Salary) | G27: {=_xlws.FILTER(A2:B21,D2:D21>100000, "No Employee Found")} -> #NAME? | J27: Emp ID | L27: 3005
A28: Marketing | B28: =COUNTIFS(C2:C21,"marketing",D2:D21,">80000") -> 2 | D28: Dept name | E28: HR | J28: salary | L28: =VLOOKUP(L27,A2:E21,4,0) -> 54149
A29: Finance | B29: =COUNTIFS(C2:C21,"finance",D2:D21,">80000") -> 4 | D29: Total Salary | E29: =SUMIFS(D2:D21, C2:C21, E28) -> 417713
D32: Off set (Top 10 avg)
D33: Avg salary | E33: =AVERAGE(OFFSET(D2,0,0,10)) -> 75081.2
